odoo/addons/helpdesk_automatic_stage_changes/CHANGELOG.md
odoo/addons/helpdesk_automatic_stage_changes/README.rst
odoo/addons/helpdesk_automatic_stage_changes/__init__.py
odoo/addons/helpdesk_automatic_stage_changes/__manifest__.py
odoo/addons/helpdesk_automatic_stage_changes/requirements.txt
odoo/addons/helpdesk_automatic_stage_changes/data/helpdesk_data.xml
odoo/addons/helpdesk_automatic_stage_changes/i18n/ca_ES.po
odoo/addons/helpdesk_automatic_stage_changes/i18n/en_US.po
odoo/addons/helpdesk_automatic_stage_changes/i18n/es.po
odoo/addons/helpdesk_automatic_stage_changes/models/__init__.py
odoo/addons/helpdesk_automatic_stage_changes/models/helpdesk_stage.py
odoo/addons/helpdesk_automatic_stage_changes/models/helpdesk_ticket.py
odoo/addons/helpdesk_automatic_stage_changes/models/mail_message.py
odoo/addons/helpdesk_automatic_stage_changes/static/description/icon.png
odoo/addons/helpdesk_automatic_stage_changes/static/src/css/font-awesome.min.css
odoo/addons/helpdesk_automatic_stage_changes/static/src/css/list_renderer.css
odoo/addons/helpdesk_automatic_stage_changes/static/src/fonts/FontAwesome.otf
odoo/addons/helpdesk_automatic_stage_changes/static/src/fonts/fontawesome-webfont.eot
odoo/addons/helpdesk_automatic_stage_changes/static/src/fonts/fontawesome-webfont.svg
odoo/addons/helpdesk_automatic_stage_changes/static/src/fonts/fontawesome-webfont.ttf
odoo/addons/helpdesk_automatic_stage_changes/static/src/fonts/fontawesome-webfont.woff
odoo/addons/helpdesk_automatic_stage_changes/static/src/fonts/fontawesome-webfont.woff2
odoo/addons/helpdesk_automatic_stage_changes/static/src/js/list_renderer.js
odoo/addons/helpdesk_automatic_stage_changes/tests/__init__.py
odoo/addons/helpdesk_automatic_stage_changes/tests/test_automatic_stage_changes.py
odoo/addons/helpdesk_automatic_stage_changes/views/helpdesk_ticket_stage_view.xml
odoo/addons/helpdesk_automatic_stage_changes/views/helpdesk_ticket_view.xml
odoo12_addon_helpdesk_automatic_stage_changes-12.0.0.2.5.dist-info/METADATA
odoo12_addon_helpdesk_automatic_stage_changes-12.0.0.2.5.dist-info/WHEEL
odoo12_addon_helpdesk_automatic_stage_changes-12.0.0.2.5.dist-info/top_level.txt
odoo12_addon_helpdesk_automatic_stage_changes-12.0.0.2.5.dist-info/RECORD
